docbrutils/__init__.py
docbrutils/cnpj.py
docbrutils/cpf.py
docbrutils-0.1.0.dist-info/licenses/LICENSE
tests/__init__.py
tests/test_cnpj.py
tests/test_cpf.py
docbrutils-0.1.0.dist-info/METADATA
docbrutils-0.1.0.dist-info/WHEEL
docbrutils-0.1.0.dist-info/top_level.txt
docbrutils-0.1.0.dist-info/RECORD
