Metadata-Version: 2.4
Name: docbrutils
Version: 0.1.0
Summary: Validação e geração de CPF e CNPJ
Home-page: https://github.com/mauriciocampos1234/docbrutils
Author: Maurício Campos
Author-email: mauriciocamposdev@gmail.com
Classifier: Programming Language :: Python :: 3
Classifier: License :: OSI Approved :: MIT License
Requires-Python: >=3.7
License-File: LICENSE
Dynamic: author
Dynamic: author-email
Dynamic: classifier
Dynamic: description
Dynamic: description-content-type
Dynamic: home-page
Dynamic: license-file
Dynamic: requires-python
Dynamic: summary
